LICENSE
README.rst
setup.cfg
setup.py
qnnlib/__init__.py
qnnlib/qnnlib.py
qnnlib/qnnlib_bak.py
qnnlib/test_changeoptimizer.py
qnnlib/test_diabetescase.py
qnnlib/test_ibmq.py
qnnlib/test_normalcase.py
qnnlib/test_normalcase2.py
qnnlib/test_normalcase3.py
qnnlib/test_predict.py
qnnlib.egg-info/PKG-INFO
qnnlib.egg-info/SOURCES.txt
qnnlib.egg-info/dependency_links.txt
qnnlib.egg-info/requires.txt
qnnlib.egg-info/top_level.txt