Metadata-Version: 2.1
Name: qnnlib
Version: 0.1.6
Summary: This library is designed to help data scientists easily conduct experiments with Quantum Neural Networks (QNNs) without the need to manually construct quantum circuits. 
Home-page: https://github.com/chinnapongpsu/qnnlib
Download-URL: https://github.com/chinnapongpsu/qnnlib/archive/refs/tags/0.1.5.zip
Author: chinnapongpsu
Author-email: chinnapong.a@psu.ac.th
License: MIT
Keywords: quantum neural networks,quantum machine learningzzfeaturemap,twolocal
Classifier: Development Status :: 3 - Alpha
Classifier: Intended Audience :: Education
Classifier: Topic :: Utilities
Classifier: License :: OSI Approved :: MIT License
Classifier: Programming Language :: Python :: 3.11
License-File: LICENSE
Requires-Dist: scikit-learn==1.5.1
Requires-Dist: tensorflow
Requires-Dist: tf_keras
Requires-Dist: pennylane==0.37.0
Requires-Dist: matplotlib
Requires-Dist: pandas
Requires-Dist: qiskit-ibm-provider==0.11.0
Requires-Dist: pennylane-qiskit
